simq-0.1.1.dist-info/METADATA
simq-0.1.1.dist-info/WHEEL
simq-0.1.1.dist-info/entry_points.txt
simq-0.1.1.dist-info/licenses/LICENSE
simq/__init__.py
simq/core.py
simq/routers.py
simq-0.1.1.dist-info/RECORD
